permissive_dict/__init__.py
permissive_dict-1.0.4.dist-info/LICENSE
permissive_dict-1.0.4.dist-info/METADATA
permissive_dict-1.0.4.dist-info/WHEEL
permissive_dict-1.0.4.dist-info/top_level.txt
permissive_dict-1.0.4.dist-info/RECORD
