Metadata-Version: 2.1
Name: permissive-dict
Version: 1.0.4
Summary: Dictionary with loose rules for finding keys.
Home-page: https://github.com/Martlark/PermissiveDict
Author: Andrew Rowe
Author-email: rowe.andrew.d@gmail.com
License: Apache Software License
Download-URL: https://github.com/Martlark/PermissiveDict/archive/1.0.4.tar.gz
Keywords: dictionary dict
Platform: UNKNOWN
Classifier: Development Status :: 5 - Production/Stable
Classifier: Intended Audience :: Developers
Classifier: Topic :: Software Development :: Libraries :: Python Modules
Classifier: License :: OSI Approved :: Apache Software License
Classifier: Programming Language :: Python
Classifier: Programming Language :: Python :: 3
Classifier: Programming Language :: Python :: 3.4
Classifier: Programming Language :: Python :: 3.5
Classifier: Programming Language :: Python :: 3.6
Classifier: Programming Language :: Python :: 3.7
Classifier: Operating System :: POSIX
Classifier: Operating System :: MacOS
Classifier: Operating System :: Unix
Classifier: Operating System :: Microsoft :: Windows
